czpubtran/__init__.py
czpubtran/api.py
czpubtran-0.2.1.dist-info/LICENSE
czpubtran-0.2.1.dist-info/METADATA
czpubtran-0.2.1.dist-info/WHEEL
czpubtran-0.2.1.dist-info/top_level.txt
czpubtran-0.2.1.dist-info/RECORD
