Metadata-Version: 2.1
Name: czpubtran
Version: 0.2.1
Summary: Calling CHAPS REST API to get information about public transit in CZ
Home-page: https://github.com/bruxy70/CzPubTran
Author: Václav Chaloupka
Author-email: vasek.chaloupka@hotmail.com
License: MIT
Platform: UNKNOWN
Classifier: Programming Language :: Python
Classifier: Programming Language :: Python :: 3
Classifier: Programming Language :: Python :: 3.6
Classifier: Programming Language :: Python :: 3.7
Classifier: License :: OSI Approved :: MIT License
Classifier: Operating System :: OS Independent
Classifier: Intended Audience :: Developers
Requires-Python: >=3.6.0
Requires-Dist: asyncio
Requires-Dist: aiohttp
Requires-Dist: async-timeout
